setup.py
OrgModeIO/OrgDateTime.py
OrgModeIO/OrgDoc.py
OrgModeIO/OrgNode.py
OrgModeIO/OrgParser.py
OrgModeIO/__init__.py
OrgModeIO.egg-info/PKG-INFO
OrgModeIO.egg-info/SOURCES.txt
OrgModeIO.egg-info/dependency_links.txt
OrgModeIO.egg-info/top_level.txt