Metadata-Version: 1.0
Name: OrgModeIO
Version: 0.1.4
Summary: This is a python library for parsing Emacs org-mode files and write to html or others
Home-page: https://github.com/auzn/OrgModeIO
Author: auzn
Author-email: auzn.cn@gmail.com
License: MIT
Keywords: org mode
Platform: UNKNOWN
